SQLParserDataPipeline/From.py
SQLParserDataPipeline/Select.py
SQLParserDataPipeline/Unnest.py
SQLParserDataPipeline/__init__.py
SQLParserDataPipeline-1.0.dist-info/METADATA
SQLParserDataPipeline-1.0.dist-info/WHEEL
SQLParserDataPipeline-1.0.dist-info/top_level.txt
SQLParserDataPipeline-1.0.dist-info/RECORD
