Metadata-Version: 2.1
Name: SQLParserDataPipeline
Version: 1.0
Summary: The SQLParserDataPipeline Library is a powerful Python package designed for parsing and interpreting complex SQL queries. It was developed with a focus on BigQuery but is adaptable to other SQL dialects due to its flexible parsing strategy that doesn't consider the function itself but the most inner parentheses.
Author: Emanuele Iaccarino
Author-email: emanueleiaccarino.ei@gmail.com
Classifier: Development Status :: 3 - Alpha
Classifier: Intended Audience :: Developers
Classifier: Topic :: Software Development :: Libraries
Classifier: License :: OSI Approved :: MIT License
Classifier: Programming Language :: Python :: 3
Classifier: Programming Language :: Python :: 3.6
Classifier: Programming Language :: Python :: 3.7
Classifier: Programming Language :: Python :: 3.8
Classifier: Programming Language :: Python :: 3.9
Requires-Python: >=3.6
